nmrpystar/__init__.py
nmrpystar/cleantokens.py
nmrpystar/hierarchical.py
nmrpystar/nmrstarast.py
nmrpystar/parser.py
nmrpystar/scanner.py
nmrpystar/starast.py
nmrpystar/unparse/__init__.py
nmrpystar/unparse/combinators.py
nmrpystar/unparse/cst.py
nmrpystar/unparse/maybeerror.py
NMRPyStar-1.0.0.dist-info/LICENSE.txt
NMRPyStar-1.0.0.dist-info/METADATA
NMRPyStar-1.0.0.dist-info/WHEEL
NMRPyStar-1.0.0.dist-info/top_level.txt
NMRPyStar-1.0.0.dist-info/RECORD
