Metadata-Version: 2.1
Name: NMRPyStar
Version: 1.0.0
Summary: a parser for the NMR-STAR data format
Home-page: https://github.com/mattfenwick/NMRPyStar
Author: Matt Fenwick
Author-email: mfenwick100@gmail.com
License: MIT
Platform: UNKNOWN
Classifier: License :: OSI Approved :: MIT License
Classifier: Programming Language :: Python
Classifier: Programming Language :: Python :: 3.5
Classifier: Programming Language :: Python :: 3.6
Classifier: Programming Language :: Python :: 3.7
Classifier: Programming Language :: Python :: 3.8
Classifier: Topic :: Software Development :: Libraries
Classifier: Topic :: Software Development :: Libraries :: Python Modules
Classifier: Intended Audience :: Developers
Requires-Python: >=3.5
